ezmodeller/__init__.py
ezmodeller/collections.py
ezmodeller/errors.py
ezmodeller/model_constraint.py
ezmodeller/model_objective.py
ezmodeller/model_variable.py
ezmodeller/optimization_model.py
ezmodeller-0.1.3.dist-info/licenses/LICENSE
ezmodeller-0.1.3.dist-info/METADATA
ezmodeller-0.1.3.dist-info/WHEEL
ezmodeller-0.1.3.dist-info/top_level.txt
ezmodeller-0.1.3.dist-info/RECORD
