Metadata-Version: 2.4
Name: ezmodeller
Version: 0.1.3
Summary: Package to allow for easy/structured modeling and splitting up your model into multiple files
Author-email: Guido Diepen <site-ezmodeller@guidodiepen.nl>
License-Expression: Apache-2.0
Project-URL: Homepage, https://github.com/gdiepen/ezmodeller
Project-URL: Bug Tracker, https://github.com/gdiepen/ezmodeller/issues
Project-URL: Documentation, https://github.com/gdiepen/ezmodeller
Classifier: Programming Language :: Python :: 3
Classifier: Operating System :: OS Independent
Requires-Python: >=3.10
License-File: LICENSE
Requires-Dist: gurobipy>=10.0.0
Dynamic: license-file
